b4rpipe/CreateMs2.py
b4rpipe/LibB4Rtools.py
b4rpipe/LibB4Rtools2.py
b4rpipe/LibB4Rtools_v0.py
b4rpipe/__init__.py
b4rpipe/b4rquery.py
b4rpipe/godec.py
b4rpipe/main.py
b4rpipe/makedatalist.py
b4rpipe/specfile4.py
b4rpipe-0.1.3.dist-info/METADATA
b4rpipe-0.1.3.dist-info/WHEEL
b4rpipe-0.1.3.dist-info/top_level.txt
b4rpipe-0.1.3.dist-info/RECORD
