Metadata-Version: 2.1
Name: b4rpipe
Version: 0.1.3
Summary: Pipeline reduction tools for B4R (2mm heterodyne reciver) on LMT 50m @Mexico
Home-page: https://github.com/LMT-heterodyne-dev/b4rpipe
Author: astroysmr
Author-email: astro.yoshimura@gmail.com
License: MIT
Keywords: B4R LMT
Platform: UNKNOWN
Classifier: License :: OSI Approved :: MIT License
Classifier: Programming Language :: Python :: 3.6
Classifier: Programming Language :: Python :: 3.7
Classifier: Programming Language :: Python :: 3.8
Requires-Dist: numpy
Requires-Dist: scipy
Requires-Dist: astropy
Requires-Dist: matplotlib
Requires-Dist: netcdf4
Requires-Dist: python-casacore
Requires-Dist: tqdm
Requires-Dist: sklearn
